{
  "tweets": [
    {
      "id": "1496582784240037901",
      "text": "LeBron fans will love this stat https://t.co/nroViGlZcV"
    },
    {
      "id": "1495865450999455745",
      "text": "Jokic is great \uD83D\uDE02\n\nh/t @msinger https://t.co/b8iFrkWQ9T"
    },
    {
      "id": "1495833031340605440",
      "text": "Pretty impressive stuff from @iamSauceGardner \uD83D\uDD25\n\nh/t @FieldYates https://t.co/gBQv1NkyT9"
    },
    {
      "id": "1494815484910313472",
      "text": "Y'all agree with this take? https://t.co/UnPp9xq1Wk"
    },
    {
      "id": "1494781716833046529",
      "text": "How Kyler Murray fared this year with and without D-hop in the lineup https://t.co/y2TBeCcqmE"
    }
  ]
}
